minkemap/__init__.py
minkemap/cli.py
minkemap/genomering.py
minkemap/utils/__init__.py
minkemap/utils/aligner.py
minkemap/utils/parser.py
minkemap/utils/stats.py
minkemap-0.1.0.dist-info/licenses/LICENSE
minkemap-0.1.0.dist-info/METADATA
minkemap-0.1.0.dist-info/WHEEL
minkemap-0.1.0.dist-info/entry_points.txt
minkemap-0.1.0.dist-info/top_level.txt
minkemap-0.1.0.dist-info/RECORD
