Metadata-Version: 2.4
Name: minkemap
Version: 0.1.0
Summary: A Python-based Circular Genome Visualization Tool
Author-email: Erin Young <eriny@utah.gov>
License: MIT
Project-URL: Homepage, https://github.com/erinyoung/minkemap
Project-URL: Repository, https://github.com/erinyoung/minkemap
Project-URL: Bug Tracker, https://github.com/erinyoung/minkemap/issues
Keywords: bioinformatics,genomics,visualization,circular,plot
Classifier: Development Status :: 4 - Beta
Classifier: Intended Audience :: Science/Research
Classifier: Programming Language :: Python :: 3
Classifier: Topic :: Scientific/Engineering :: Bio-Informatics
Requires-Python: >=3.9
License-File: LICENSE
Requires-Dist: numpy
Requires-Dist: matplotlib
Requires-Dist: pandas
Requires-Dist: biopython
Requires-Dist: mappy
Requires-Dist: pycirclize
Dynamic: license-file
